examples/advanced_usage.py
examples/basic_usage.py
sip_client/__init__.py
sip_client/client.py
sip_client/audio/__init__.py
sip_client/audio/devices.py
sip_client/audio/manager.py
sip_client/models/__init__.py
sip_client/models/account.py
sip_client/models/call.py
sip_client/models/enums.py
sip_client/sip/__init__.py
sip_client/sip/authentication.py
sip_client/sip/messages.py
sip_client/sip/protocol.py
sip_client/utils/__init__.py
sip_client/utils/helpers.py
tests/__init__.py
tests/test_audio.py
tests/test_client.py
tests/test_sip.py
usip-1.0.0.dist-info/METADATA
usip-1.0.0.dist-info/WHEEL
usip-1.0.0.dist-info/top_level.txt
usip-1.0.0.dist-info/RECORD
