Metadata-Version: 2.4
Name: uSIP
Version: 1.0.0
Summary: A lightweight Python-based SIP client with voice support
Author-email: uSIP Development Team <support@usip.dev>
Maintainer-email: uSIP Development Team <support@usip.dev>
License: MIT
Project-URL: Homepage, https://github.com/Dashhhhhhhh/uSIP
Project-URL: Documentation, https://sip-client-library.readthedocs.io/
Project-URL: Repository, https://github.com/Dashhhhhhhh/uSIP.git
Project-URL: Issues, https://github.com/Dashhhhhhhh/uSIP/issues
Project-URL: Changelog, https://github.com/Dashhhhhhhh/uSIP/blob/main/CHANGELOG.md
Keywords: sip,voip,audio,telecommunications,rtp,telephony
Classifier: Development Status :: 4 - Beta
Classifier: Intended Audience :: Developers
Classifier: Topic :: Communications :: Telephony
Classifier: Topic :: Internet :: WWW/HTTP :: Dynamic Content
Classifier: Topic :: Software Development :: Libraries :: Python Modules
Classifier: License :: OSI Approved :: MIT License
Classifier: Programming Language :: Python :: 3
Classifier: Programming Language :: Python :: 3.8
Classifier: Programming Language :: Python :: 3.9
Classifier: Programming Language :: Python :: 3.10
Classifier: Programming Language :: Python :: 3.11
Classifier: Programming Language :: Python :: 3.12
Classifier: Operating System :: OS Independent
Requires-Python: >=3.8
Requires-Dist: pyaudio>=0.2.11
Requires-Dist: python-dotenv>=0.19.0
Requires-Dist: rich>=12.0.0
Provides-Extra: dev
Requires-Dist: pytest>=7.0.0; extra == "dev"
Requires-Dist: pytest-cov>=4.0.0; extra == "dev"
Requires-Dist: pytest-mock>=3.10.0; extra == "dev"
Requires-Dist: black>=22.0.0; extra == "dev"
Requires-Dist: isort>=5.10.0; extra == "dev"
Requires-Dist: flake8>=4.0.0; extra == "dev"
Requires-Dist: mypy>=0.950; extra == "dev"
Requires-Dist: pre-commit>=2.17.0; extra == "dev"
Provides-Extra: examples
Requires-Dist: click>=8.0.0; extra == "examples"
